{"path":"_learning/videos/progmatic-works-confirmation-popups-screens-in-powerapps.md","title":"Confirmation Popups Screens in PowerApps","excerpt":"PowerApp a Day Episode #16 (SalesPerson App) - Learn how to present your users with popup screens to confirm a harmful action.   Power App Training: https://pragmaticworks.com/Training/On-Demand-Training/Introduction-to-Powerapps  Adding spinners to our application: https://www.youtube.com/watch?v=YfYf-AkY1P8","sourceUrl":"https://everyday-cc.github.io/powerapps/api/learning/videos/progmatic-works-confirmation-popups-screens-in-powerapps/index.json","webUrl":"https://everyday.cc/powerapps/learning/videos/progmatic-works-confirmation-popups-screens-in-powerapps/","originalUrl":"https://youtube.com/watch?v=SaDEVOgOlYY","featuredContent":"<iframe width=\"800\" height=\"500\" frameborder=\"0\" src=\"https://www.youtube.com/embed/SaDEVOgOlYY\" allow=\"accelerometer; autoplay; encrypted-media; gyroscope; picture-in-picture\" allowfullscreen></iframe>","actions":null,"length":"PT10M38S","ratings":null,"provider":{"name":"Progmatic Works","domain":"pragmaticworks.com","images":null,"publishers":null,"authors":null},"publishedDateTime":"2018-09-24T11:12:20-07:00","levels":null,"topItems":null,"size":null,"heat":55,"tags":null,"images":[{"url":"https://i.ytimg.com/vi/SaDEVOgOlYY/hqdefault.jpg","width":480,"height":360,"title":null,"attribution":null,"isCached":true}],"content":"\r\n","type":"video","price":"Free","topics":["Power Apps"]}