{"path":"_learning/videos/powerapps911-powerapps-azure-blob-storage-connector.md","title":"powerapps azure blob storage connector","excerpt":"In this video, you will learn about the PowerApps Azure Blob Storage connector. We will walk through how to setup an Azure Blob Storage account, how to use Azure Storage Explorer, and finally how to use Azure Blob Storage with PowerApps. If you need to work with files with your PowerApps you need this","sourceUrl":"https://everyday-cc.github.io/powerapps/api/learning/videos/powerapps911-powerapps-azure-blob-storage-connector/index.json","webUrl":"https://everyday.cc/powerapps/learning/videos/powerapps911-powerapps-azure-blob-storage-connector/","originalUrl":"https://youtube.com/watch?v=wF0MmiaGO_o","featuredContent":"<iframe width=\"800\" height=\"500\" frameborder=\"0\" src=\"https://www.youtube.com/embed/wF0MmiaGO_o\" allow=\"accelerometer; autoplay; encrypted-media; gyroscope; picture-in-picture\" allowfullscreen></iframe>","actions":null,"length":"PT35M59S","ratings":null,"provider":{"name":"PowerApps911","domain":"powerapps911.com","images":null,"publishers":null,"authors":null},"publishedDateTime":"2019-01-13T15:51:07-08:00","levels":null,"topItems":null,"size":null,"heat":52,"tags":null,"images":[{"url":"https://i.ytimg.com/vi/wF0MmiaGO_o/maxresdefault.jpg","width":1280,"height":720,"title":null,"attribution":null,"isCached":true}],"content":"\r\n","type":"video","price":"Free","topics":["Power Apps"]}