{"path":"_learning/videos/powerapps911-powerapps-string-manipulation.md","title":"PowerApps String Manipulation","excerpt":"In this video, you will learn about how to do string manipulation in PowerApps. This core skill helps you when you need to change text that comes from users or data sources to meet your needs. Functions covered include: * Left * Right * Mid * Substitute  * Replace * Find * Len  Check out our upcoming","sourceUrl":"https://everyday-cc.github.io/powerapps/api/learning/videos/powerapps911-powerapps-string-manipulation/index.json","webUrl":"https://everyday.cc/powerapps/learning/videos/powerapps911-powerapps-string-manipulation/","originalUrl":"https://youtube.com/watch?v=1tUkZJ3VM3g","featuredContent":"<iframe width=\"800\" height=\"500\" frameborder=\"0\" src=\"https://www.youtube.com/embed/1tUkZJ3VM3g\" allow=\"accelerometer; autoplay; encrypted-media; gyroscope; picture-in-picture\" allowfullscreen></iframe>","actions":null,"length":"PT27M58S","ratings":null,"provider":{"name":"PowerApps911","domain":"powerapps911.com","images":null,"publishers":null,"authors":null},"publishedDateTime":"2018-10-14T13:26:33-07:00","levels":null,"topItems":null,"size":null,"heat":53,"tags":null,"images":[{"url":"https://i.ytimg.com/vi/1tUkZJ3VM3g/maxresdefault.jpg","width":1280,"height":720,"title":null,"attribution":null,"isCached":true}],"content":"\r\n","type":"video","price":"Free","topics":["Power Apps"]}