{"path":"_learning/courses/microsoft-learn-work-with-external-data.md","title":"Work with external data in a Power Apps canvas app","excerpt":"Do you need to connect an app to access data? Then this module is for you. It focuses on connecting your app to a data source.","sourceUrl":"https://everyday-cc.github.io/powerapps/api/learning/courses/microsoft-learn-work-with-external-data/index.json","webUrl":"https://docs.microsoft.com/en-us/learn/modules/work-with-external-data/","originalUrl":null,"featuredContent":null,"actions":null,"length":"PT58M","ratings":{"count":1179,"average":4.585242},"provider":{"name":"Microsoft Learn","domain":"microsoft.com","images":[{"url":"https://everyday-cc.github.io/powerapps/assets/images/organizations/microsoft.com-50x50.jpg","width":50,"height":50,"title":null,"attribution":null,"isCached":false}],"publishers":null,"authors":null},"publishedDateTime":null,"levels":["Intermediate"],"topItems":null,"size":null,"heat":51,"tags":null,"images":null,"content":"\r\n","type":"course","price":"Free","topics":["Power Apps","Canvas apps"]}