{
  "page": 1,
  "value": [
    {
      "path": "_news/2020-09-24-deprecation-of-time-zone-entities-in-common-data-service.md",
      "title": "Deprecation of time zone entities in Common Data Service",
      "excerpt": "The internal time zone service in Common Data Service is being deprecated in favor of using the Windows API for all time zone calculations. This means that we are restructuring the time zone entities in Common Data Service and changing the way things work.",
      "sourceUrl": null,
      "webUrl": "https://powerapps.microsoft.com/en-us/blog/deprecation-of-time-zone-entities-in-common-data-service/",
      "originalUrl": "https://powerapps.microsoft.com/en-us/blog/deprecation-of-time-zone-entities-in-common-data-service/",
      "featuredContent": null,
      "highlight": null,
      "heat": 89,
      "tags": null,
      "images": [
        {
          "url": "https://powerapps.microsoft.com/images/shared/social/social-default-image.png",
          "width": 1600,
          "height": 1600,
          "title": null,
          "attribution": null,
          "isCached": true
        }
      ],
      "content": "",
      "type": "article",
      "ampWebUrl": null,
      "cdnAmpWebUrl": null,
      "publishedDateTime": "2020-09-24T09:10:00Z",
      "updatedDateTime": null,
      "provider": {
        "name": "Microsoft",
        "domain": "microsoft.com",
        "images": [
          {
            "url": "https://everyday-cc.github.io/powerapps/assets/images/organizations/microsoft.com-50x50.jpg",
            "width": 50,
            "height": 50,
            "title": null,
            "attribution": null,
            "isCached": false
          }
        ],
        "publishers": null,
        "authors": null
      },
      "locale": "en-us",
      "categories": [
        "news"
      ],
      "topics": [
        "Power Apps",
        "Common Data Service"
      ]
    }
  ],
  "nextPage": null
}